tnpy/__init__.py
tnpy/config.toml
tnpy/exact_diagonalization.py
tnpy/finite_dmrg.py
tnpy/finite_tdvp.py
tnpy/linalg.py
tnpy/matrix_product_state.py
tnpy/model/__init__.py
tnpy/model/dimer_xxz.py
tnpy/model/model_base.py
tnpy/model/random_heisenberg.py
tnpy/model/thirring.py
tnpy/model/total_sz.py
tnpy/model/utils.py
tnpy/model/xxz.py
tnpy/operators.py
tnpy/tsdrg.py
tnpy-0.1.0.dist-info/LICENSE
tnpy-0.1.0.dist-info/WHEEL
tnpy-0.1.0.dist-info/METADATA
tnpy-0.1.0.dist-info/RECORD
