Metadata-Version: 2.1
Name: tnpy
Version: 0.1.0
Summary: Tensor Network algorithms implemented in python.
Home-page: https://github.com/tanlin2013/tnpy
Keywords: tensornetwork,quantum-mechanics,quantum-algorithms
Author: taolin
Author-email: tanlin2013@gmail.com
Requires-Python: >=3.10,<3.11
Classifier: Programming Language :: Python :: 3
Classifier: Programming Language :: Python :: 3.10
Requires-Dist: autoray (==0.2.5)
Requires-Dist: graphviz (==0.20)
Requires-Dist: h5py (==3.6.0)
Requires-Dist: numpy (==1.21.6)
Requires-Dist: primme (==3.2.1)
Requires-Dist: quimb (==1.3.0)
Requires-Dist: scipy (==1.8.0)
Requires-Dist: tensornetwork (==0.4.6)
Requires-Dist: toml (>=0.10.2,<0.11.0)
Requires-Dist: tqdm (>=4.63.0,<5.0.0)
Project-URL: Documentation, https://tanlin2013.github.io/tnpy/
